congruity/__init__.py
congruity/helper/__init__.py
congruity/helper/patch.py
congruity/helper/rdd.py
congruity/json_conversion.py
congruity/patch.py
congruity/rdd_adapter.py
congruity/spark_context_adapter.py
spark_congruity-0.0.1rc5.dist-info/LICENSE
spark_congruity-0.0.1rc5.dist-info/METADATA
spark_congruity-0.0.1rc5.dist-info/NOTICE
spark_congruity-0.0.1rc5.dist-info/WHEEL
spark_congruity-0.0.1rc5.dist-info/RECORD
